LICENSE
MANIFEST.in
README.md
pyproject.toml
linlei04_mypkg1.egg-info/PKG-INFO
linlei04_mypkg1.egg-info/SOURCES.txt
linlei04_mypkg1.egg-info/dependency_links.txt
linlei04_mypkg1.egg-info/entry_points.txt
linlei04_mypkg1.egg-info/requires.txt
linlei04_mypkg1.egg-info/top_level.txt
mypkg1/__init__.py
mypkg1/__main__.py
mypkg1/add.py
mypkg1/ext.rst