Metadata-Version: 2.1
Name: linlei04-mypkg1
Version: 1.0.4
Summary: My package description
License: MIT
Project-URL: Homepage, https://github.com/xmlclone/docode
Project-URL: Documentation, https://github.com/xmlclone/docode
Project-URL: Code, https://github.com/xmlclone/docode
Project-URL: Help/Questions, https://github.com/xmlclone/docode
Project-URL: Issue tracker, https://github.com/xmlclone/docode
Requires-Python: >=3.7
License-File: LICENSE
Requires-Dist: requests
Requires-Dist: selenium==4.14.0
